hexagon/__init__.py
hexagon/__main__.py
hexagon/actions/__init__.py
hexagon/actions/__templates/__init__.py
hexagon/actions/__templates/custom_tool/__init__.py
hexagon/actions/external/__init__.py
hexagon/actions/external/open_link.py
hexagon/actions/internal/__init__.py
hexagon/actions/internal/create_new_tool.py
hexagon/actions/internal/install_cli.py
hexagon/actions/internal/replay.py
hexagon/actions/internal/save_new_alias.py
hexagon/actions/internal/schema.py
hexagon/actions/internal/update_cli.py
hexagon/actions/internal/update_hexagon.py
hexagon/domain/__init__.py
hexagon/domain/cli.py
hexagon/domain/env.py
hexagon/domain/hexagon_error.py
hexagon/domain/hooks/__init__.py
hexagon/domain/hooks/execution.py
hexagon/domain/hooks/wax.py
hexagon/domain/tool/__init__.py
hexagon/runtime/__init__.py
hexagon/runtime/configuration.py
hexagon/runtime/help.py
hexagon/runtime/options.py
hexagon/runtime/parse_args.py
hexagon/runtime/singletons.py
hexagon/runtime/version.py
hexagon/runtime/wax.py
hexagon/runtime/yaml.py
hexagon/runtime/cwd_tools/__init__.py
hexagon/runtime/dependencies/__init__.py
hexagon/runtime/dependencies/fs.py
hexagon/runtime/dependencies/node.py
hexagon/runtime/dependencies/python.py
hexagon/runtime/execute/__init__.py
hexagon/runtime/execute/action.py
hexagon/runtime/execute/errors.py
hexagon/runtime/execute/execution_hook.py
hexagon/runtime/execute/tool.py
hexagon/runtime/plugins/__init__.py
hexagon/runtime/update/__init__.py
hexagon/runtime/update/github.py
hexagon/runtime/update/hexagon.py
hexagon/runtime/update/shared.py
hexagon/runtime/update/silent_fail.py
hexagon/runtime/update/version.py
hexagon/runtime/update/changelog/__init__.py
hexagon/runtime/update/changelog/fetch.py
hexagon/runtime/update/changelog/format.py
hexagon/runtime/update/changelog/parse.py
hexagon/runtime/update/cli/__init__.py
hexagon/runtime/update/cli/command.py
hexagon/runtime/update/cli/git.py
hexagon/support/__init__.py
hexagon/support/tracer.py
hexagon-0.64.3.dist-info/licenses/LICENSE
hexagon-0.64.3.dist-info/METADATA
hexagon-0.64.3.dist-info/WHEEL
hexagon-0.64.3.dist-info/entry_points.txt
hexagon-0.64.3.dist-info/top_level.txt
hexagon-0.64.3.dist-info/RECORD
