Metadata-Version: 2.4
Name: hexagon
Version: 0.64.3
Summary: Build your Team's CLI
Home-page: https://github.com/lt-mayonesa/hexagon
Author: Joaco Campero
Author-email: juacocampero@gmail.com
Project-URL: Bug Tracker, https://github.com/lt-mayonesa/hexagon/issues
Classifier: Programming Language :: Python :: 3
Classifier: License :: OSI Approved :: MIT License
Classifier: Operating System :: OS Independent
Requires-Python: >=3.10
License-File: LICENSE
Requires-Dist: annotated-types==0.7.0; python_version >= "3.8"
Requires-Dist: clipboard==0.0.4
Requires-Dist: inquirerpy==0.3.4; python_version >= "3.7" and python_version < "4.0"
Requires-Dist: markdown==3.10; python_version >= "3.10"
Requires-Dist: markdown-it-py==4.0.0; python_version >= "3.10"
Requires-Dist: mdurl==0.1.2; python_version >= "3.7"
Requires-Dist: packaging==25.0; python_version >= "3.8"
Requires-Dist: pfzy==0.3.4; python_version >= "3.7" and python_version < "4.0"
Requires-Dist: prompt-toolkit==3.0.52; python_version >= "3.8"
Requires-Dist: pydantic==2.12.5; python_version >= "3.9"
Requires-Dist: pydantic-core==2.41.5; python_version >= "3.9"
Requires-Dist: pydantic-settings==2.12.0; python_version >= "3.10"
Requires-Dist: pygments==2.19.2; python_version >= "3.8"
Requires-Dist: pyperclip==1.11.0
Requires-Dist: python-dotenv==1.2.1; python_version >= "3.9"
Requires-Dist: rich==14.2.0; python_full_version >= "3.8.0"
Requires-Dist: ruamel.yaml==0.19.0; python_version >= "3.9"
Requires-Dist: ruamel.yaml.clibz==0.3.4; python_version >= "3.9"
Requires-Dist: typing-extensions==4.15.0; python_version >= "3.9"
Requires-Dist: typing-inspection==0.4.2; python_version >= "3.9"
Requires-Dist: wcwidth==0.2.14; python_version >= "3.6"
Dynamic: author
Dynamic: author-email
Dynamic: classifier
Dynamic: description
Dynamic: description-content-type
Dynamic: home-page
Dynamic: license-file
Dynamic: project-url
Dynamic: requires-dist
Dynamic: requires-python
Dynamic: summary
